cardlatex/__init__.py
cardlatex/__main__.py
cardlatex/__version__.py
cardlatex/config.py
cardlatex/image.py
cardlatex/pdf.py
cardlatex/template.py
cardlatex/template.tex
cardlatex/tex.py
cardlatex-0.5.7.dist-info/LICENSE
cardlatex-0.5.7.dist-info/METADATA
cardlatex-0.5.7.dist-info/WHEEL
cardlatex-0.5.7.dist-info/entry_points.txt
cardlatex-0.5.7.dist-info/top_level.txt
cardlatex-0.5.7.dist-info/RECORD
